{"FirstTeam": {"Goals_scored": "2 0 2", "Total_attemps": "4 3 7", "One_target": "4 1 5", "Off_target": "0 1 1", "Blocked": "0 1 1", "Woodwork": "0 0 0", "Saves": "0 3 3", "Corners": "1 1 2", "Offsides": "0 3 3", "Total_time_played": "47'02\" 51'19\" 98'21\"", "Ball_possession": "32% 43% 37%", "Yellow_cards": "0 1 1", "Red_cards": "0 1 1", "Fouls_committed": "4 4 8", "Fouls_suffered": "3 4 7", "Passes_attemted": "163 151 314", "Short_Passes_attemted": "43 22 65", "Medium_Passes_attemted": "93 96 189", "Long_Passes_attemted": "27 33 60", "Passes_completed": "119 117 236", "Short_Passes_completed": "30 19 49", "Medium_Passes_completed": "77 83 160", "Long_Passes_completed": "12 15 27", "Pass_completion_rate": "73% 77% 75%", "Short_rate": "70% 86% 75%", "Medium_rate": "83% 86% 85%", "Long_rate": "44% 45% 45%", "Into_the_attacking_third": "9/8 12/9 21/17", "Into_the_key_area": "4/8 9/5 13/13", "Into_the_penalty_area": "4/5 4/0 8/5"}, "SecondTeam": {"Goals_scored": "2 1 3", "Total_attemps": "4 7 11", "One_target": "2 4 6", "Off_target": "1 2 3", "Blocked": "1 1 2", "Woodwork": "0 0 0", "Saves": "2 1 3", "Corners": "0 5 5", "Offsides": "1 0 1", "Total_time_played": "47'02\" 51'19\" 98'21\"", "Ball_possession": "68% 57% 63%", "Yellow_cards": "0 2 2", "Red_cards": "0 0 0", "Fouls_committed": "4 5 9", "Fouls_suffered": "4 4 8", "Passes_attemted": "388 281 669", "Short_Passes_attemted": "83 79 162", "Medium_Passes_attemted": "266 169 435", "Long_Passes_attemted": "39 34 73", "Passes_completed": "346 242 588", "Short_Passes_completed": "70 70 140", "Medium_Passes_completed": "250 154 404", "Long_Passes_completed": "26 19 45", "Pass_completion_rate": "89% 86% 88%", "Short_rate": "84% 89% 86%", "Medium_rate": "94% 91% 93%", "Long_rate": "67% 56% 62%", "Into_the_attacking_third": "25/13 26/10 51/23", "Into_the_key_area": "19/8 9/9 28/17", "Into_the_penalty_area": "3/4 7/3 10/7"}}