{"FirstTeam": {"Goals_scored": "0 2 2", "Total_attemps": "1 6 7", "One_target": "0 4 4", "Off_target": "1 0 1", "Blocked": "0 2 2", "Woodwork": "0 0 0", "Saves": "5 3 8", "Corners": "0 2 2", "Offsides": "0 0 0", "Total_time_played": "47'59\" 49'04\" 97'03\"", "Ball_possession": "46% 42% 44%", "Distance_covered": "54014 57800 111814", "Yellow_cards": "0 0 0", "Red_cards": "0 0 0", "Fouls_committed": "5 5 10", "Fouls_suffered": "9 6 15", "Passes_attemted": "232 188 420", "Short_Passes_attemted": "44 41 85", "Medium_Passes_attemted": "158 108 266", "Long_Passes_attemted": "30 39 69", "Passes_completed": "198 153 351", "Short_Passes_completed": "33 33 66", "Medium_Passes_completed": "144 97 241", "Long_Passes_completed": "21 23 44", "Pass_completion_rate": "85% 81% 84%", "Short_rate": "75% 80% 78%", "Medium_rate": "91% 90% 91%", "Long_rate": "70% 59% 64%", "Into_the_attacking_third": "8/3 14/8 22/11", "Into_the_key_area": "5/4 10/5 15/9", "Into_the_penalty_area": "4/2 4/4 8/6"}, "SecondTeam": {"Goals_scored": "0 0 0", "Total_attemps": "7 8 15", "One_target": "4 3 7", "Off_target": "2 2 4", "Blocked": "1 3 4", "Woodwork": "1 0 1", "Saves": "0 2 2", "Corners": "7 4 11", "Offsides": "1 2 3", "Total_time_played": "47'59\" 49'04\" 97'03\"", "Ball_possession": "54% 58% 56%", "Distance_covered": "55894 55329 111223", "Yellow_cards": "1 0 1", "Red_cards": "0 0 0", "Fouls_committed": "9 6 15", "Fouls_suffered": "4 4 8", "Passes_attemted": "300 295 595", "Short_Passes_attemted": "65 71 136", "Medium_Passes_attemted": "201 180 381", "Long_Passes_attemted": "34 44 78", "Passes_completed": "262 255 517", "Short_Passes_completed": "51 66 117", "Medium_Passes_completed": "187 159 346", "Long_Passes_completed": "24 30 54", "Pass_completion_rate": "87% 86% 87%", "Short_rate": "78% 93% 86%", "Medium_rate": "93% 88% 91%", "Long_rate": "71% 68% 69%", "Into_the_attacking_third": "31/8 24/9 55/17", "Into_the_key_area": "18/8 10/6 28/14", "Into_the_penalty_area": "8/2 6/6 14/8"}}